{
//A List of frames
	"Copper":{
		//The display name of the frame(required)
		"name":"frame.ore.copper",
		//The rgb color of the frame(optional default: 255,255,255)
		"ColorRed":195,
		"ColorGreen":125,
		"ColorBlue":10,
		//The frame type (optional default 0)
		//0: metal
		//1: stone
		//2: obsidian
		"FrameType":0,
		//The tier the frame is used to craft(optional 0-7(inclusive) default -1)
		//set to -1 to disable crafting(still alows painting)
		"tier":1,
		//a list of materials that can be used to craft/paint a frame(required)
		//OreDictionary value: "Ore"
		//ItemStack: {"name":"name", (optional)"meta":meta(set to "wildcard" to use any meta}, "nbt":{nbt data}}
		"materials":"ingotCopper"
	},
	"Tin":{
		"name":"frame.ore.tin",
		"ColorRed":117,
		"ColorGreen":148,
		"ColorBlue":191,
		"FrameType":0,
		"tier":1,
		"materials":"ingotTin"
	},
	"RedAlloy":{
		"name":"frame.ore.redalloy",
		"ColorRed":237,
		"ColorGreen":66,
		"ColorBlue":66,
		"FrameType":0,
		"tier":1,
		"materials":"ingotRedAlloy"
	},
	
	"Lead":{
		"name":"frame.ore.lead",
		"ColorRed":133,
		"ColorGreen":139,
		"ColorBlue":172,
		"FrameType":0,
		"tier":2,
		"materials":"ingotLead"
	},
	"Nickel":{
		"name":"frame.ore.nickel",
		"ColorRed":245,
		"ColorGreen":245,
		"ColorBlue":215,
		"FrameType":0,
		"tier":2,
		"materials":"ingotNickel"
	},
	"Bronze":{
		"name":"frame.ore.bronze",
		"ColorRed":255,
		"ColorGreen":155,
		"ColorBlue":50,
		"FrameType":0,
		"tier":2,
		"materials":"ingotBronze"
	},
	"Steel":{
		"name":"frame.ore.steel",
		"ColorRed":128,
		"ColorGreen":128,
		"ColorBlue":128,
		"FrameType":0,
		"tier":2,
		"materials":"ingotSteel"
	},
	"Thaumium":{
		"name":"frame.ore.thaumium",
		"ColorRed":80,
		"ColorGreen":65,
		"ColorBlue":120,
		"FrameType":0,
		"tier":2,
		"materials":"ingotThaumium"
	},
	"ElectrotineAlloy":{
		"name":"frame.ore.electrotinealloy",
		"ColorRed":0,
		"ColorGreen":155,
		"ColorBlue":200,
		"FrameType":0,
		"tier":2,
		"materials":"ingotElectrotineAlloy"
	},
	"Zinc":{
		"name":"frame.ore.zinc",
		"ColorRed":210,
		"ColorGreen":190,
		"ColorBlue":140,
		"FrameType":0,
		"tier":2,
		"materials":"ingotZinc"
	},
	
	"Invar":{
		"name":"frame.ore.invar",
		"ColorRed":150,
		"ColorGreen":163,
		"ColorBlue":156,
		"FrameType":0,
		"tier":3,
		"materials":"ingotInvar"
	},
	"EnergeticAlloy":{
		"name":"frame.ore.energeticalloy",
		"ColorRed":232,
		"ColorGreen":93,
		"ColorBlue":6,
		"FrameType":0,
		"tier":3,
		"materials":"ingotEnergeticAlloy"
	},
	"Atlarus":{
		"name":"frame.ore.atlarus",
		"ColorRed":204,
		"ColorGreen":179,
		"ColorBlue":0,
		"FrameType":0,
		"tier":3,
		"materials":"ingotAtlarus"
	},
	"Alduorite":{
		"name":"frame.ore.alduorite",
		"ColorRed":163,
		"ColorGreen":222,
		"ColorBlue":222,
		"FrameType":0,
		"tier":3,
		"materials":"ingotAlduorite"
	},
	"Void":{
		"name":"frame.ore.void",
		"ColorRed":29,
		"ColorGreen":18,
		"ColorBlue":42,
		"FrameType":0,
		"tier":3,
		"materials":"ingotVoid"
	},
	"Brass":{
		"name":"frame.ore.brass",
		"ColorRed":155,
		"ColorGreen":120,
		"ColorBlue":54,
		"FrameType":0,
		"tier":3,
		"materials":"ingotBrass"
	},
	
	"Silver":{
		"name":"frame.ore.silver",
		"ColorRed":147,
		"ColorGreen":178,
		"ColorBlue":201,
		"FrameType":0,
		"tier":4,
		"materials":"ingotSilver"
	},
	"Aluminum":{
		"name":"frame.ore.aluminum",
		"ColorRed":145,
		"ColorGreen":145,
		"ColorBlue":145,
		"FrameType":0,
		"tier":4,
		"materials":"ingotAluminum"
	},
	"Tungsten":{
		"name":"frame.ore.tungsten",
		"ColorRed":73,
		"ColorGreen":73,
		"ColorBlue":73,
		"FrameType":0,
		"tier":4,
		"materials":"ingotTungsten"
	},
	"Desichalkos":{
		"name":"frame.ore.desichalkos",
		"ColorRed":80,
		"ColorGreen":33,
		"ColorBlue":118,
		"FrameType":0,
		"tier":4,
		"materials":"ingotDesichalkos"
	},
	"Unstable":{
		"name":"frame.ore.unstable",
		"ColorRed":144,
		"ColorGreen":144,
		"ColorBlue":144,
		"FrameType":0,
		"tier":4,
		"materials":"ingotUnstable"
	},
	"Reinforced":{
		"name":"frame.ore.reinforced",
		"ColorRed":208,
		"ColorGreen":225,
		"ColorBlue":236,
		"FrameType":0,
		"tier":4,
		"materials":"ingotReinforced"
	},
	
	"Platinum":{
		"name":"frame.ore.platinum",
		"ColorRed":98,
		"ColorGreen":153,
		"ColorBlue":255,
		"FrameType":0,
		"tier":5,
		"materials":"ingotPlatinum"
	},
	"Mithril":{
		"name":"frame.ore.mithril",
		"ColorRed":135,
		"ColorGreen":215,
		"ColorBlue":255,
		"FrameType":0,
		"tier":5,
		"materials":"ingotMithril"
	},
	"Electrum":{
		"name":"frame.ore.electrum",
		"ColorRed":255,
		"ColorGreen":255,
		"ColorBlue":150,
		"FrameType":0,
		"tier":5,
		"materials":"ingotElectrum"
	},
	"Signalum":{
		"name":"frame.ore.signalum",
		"ColorRed":225,
		"ColorGreen":110,
		"ColorBlue":10,
		"FrameType":0,
		"tier":5,
		"materials":"ingotSignalum"
	},
	"Lumium":{
		"name":"frame.ore.lumium",
		"ColorRed":220,
		"ColorGreen":230,
		"ColorBlue":155,
		"FrameType":0,
		"tier":5,
		"materials":"ingotLumium"
	},
	"Enderium":{
		"name":"frame.ore.enderium",
		"ColorRed":20,
		"ColorGreen":150,
		"ColorBlue":150,
		"FrameType":0,
		"tier":5,
		"materials":"ingotEnderium"
	},
	"Alumite":{
		"name":"frame.ore.alumite",
		"ColorRed":235,
		"ColorGreen":140,
		"ColorBlue":240,
		"FrameType":0,
		"tier":5,
		"materials":"ingotAlumite"
	},
	"Cobalt":{
		"name":"frame.ore.cobalt",
		"ColorRed":65,
		"ColorGreen":65,
		"ColorBlue":255,
		"FrameType":0,
		"tier":5,
		"materials":"ingotCobalt"
	},
	"Ardite":{
		"name":"frame.ore.ardite",
		"ColorRed":255,
		"ColorGreen":88,
		"ColorBlue":0,
		"FrameType":0,
		"tier":5,
		"materials":"ingotArdite"
	},
	"Quicksilver":{
		"name":"frame.ore.quicksilver",
		"ColorRed":125,
		"ColorGreen":210,
		"ColorBlue":200,
		"FrameType":0,
		"tier":5,
		"materials":"ingotQuicksilver"
	},
	"ElectricalSteel":{
		"name":"frame.ore.electricalsteel",
		"ColorRed":185,
		"ColorGreen":185,
		"ColorBlue":185,
		"FrameType":0,
		"tier":5,
		"materials":"ingotElectricalSteel"
	},
	"Soularium":{
		"name":"frame.ore.soularium",
		"ColorRed":90,
		"ColorGreen":65,
		"ColorBlue":40,
		"FrameType":0,
		"tier":5,
		"materials":"ingotSoularium"
	},
	"Carbide":{
		"name":"frame.ore.carbide",
		"ColorRed":76,
		"ColorGreen":76,
		"ColorBlue":76,
		"FrameType":0,
		"tier":5,
		"materials":"ingotCarbide"
	},
	
	"Osmium":{
		"name":"frame.ore.osmium",
		"ColorRed":215,
		"ColorGreen":220,
		"ColorBlue":230,
		"FrameType":0,
		"tier":6,
		"materials":"ingotOsmium"
	},
	"Manyullyn":{
		"name":"frame.ore.manyullyn",
		"ColorRed":120,
		"ColorGreen":0,
		"ColorBlue":235,
		"FrameType":0,
		"tier":6,
		"materials":"ingotManyullyn"
	},
	"EnhancedGalgadorian":{
		"name":"frame.ore.enhancedgalgadorian",
		"ColorRed":150,
		"ColorGreen":95,
		"ColorBlue":135,
		"FrameType":0,
		"tier":6,
		"materials":"ingotEnhancedGalgadorian"
	},
	"DarkSteel":{
		"name":"frame.ore.darksteel",
		"ColorRed":121,
		"ColorGreen":121,
		"ColorBlue":121,
		"FrameType":0,
		"tier":6,
		"materials":"ingotDarkSteel"
	},
	"VibrantAlloy":{
		"name":"frame.ore.vibrantalloy",
		"ColorRed":210,
		"ColorGreen":240,
		"ColorBlue":125,
		"FrameType":0,
		"tier":6,
		"materials":"ingotVibrantAlloy"
	},
	"Infuscolium":{
		"name":"frame.ore.infuscolium",
		"ColorRed":146,
		"ColorGreen":33,
		"ColorBlue":86,
		"FrameType":0,
		"tier":6,
		"materials":"ingotInfuscolium"
	},
	"Ceruclase":{
		"name":"frame.ore.ceruclase",
		"ColorRed":70,
		"ColorGreen":140,
		"ColorBlue":170,
		"FrameType":0,
		"tier":6,
		"materials":"ingotCeruclase"
	},
	"Amordrine":{
		"name":"frame.ore.amordrine",
		"ColorRed":170,
		"ColorGreen":140,
		"ColorBlue":180,
		"FrameType":0,
		"tier":6,
		"materials":"ingotAmordrine"
	},
	
	"Vibrantium":{
		"name":"frame.ore.vibrantium",
		"ColorRed":215,
		"ColorGreen":230,
		"ColorBlue":90,
		"FrameType":0,
		"tier":7,
		"materials":"ingotVibrantium"
	},
	"Blutonium":{
		"name":"frame.ore.blutonium",
		"ColorRed":30,
		"ColorGreen":0,
		"ColorBlue":230,
		"FrameType":0,
		"tier":7,
		"materials":"ingotBlutonium"
	},
	"Bedrockium":{
		"name":"frame.ore.bedrockium",
		"ColorRed":55,
		"ColorGreen":55,
		"ColorBlue":55,
		"FrameType":0,
		"tier":7,
		"materials":"ingotBedrockium"
	}
}